sec_edgar_downloader/_Downloader.py
sec_edgar_downloader/__init__.py
sec_edgar_downloader/_constants.py
sec_edgar_downloader/_orchestrator.py
sec_edgar_downloader/_sec_gateway.py
sec_edgar_downloader/_types.py
sec_edgar_downloader/_utils.py
sec_edgar_downloader/_version.py
sec_edgar_downloader/py.typed
sec_edgar_downloader-5.0.1.dist-info/LICENSE
sec_edgar_downloader-5.0.1.dist-info/WHEEL
sec_edgar_downloader-5.0.1.dist-info/METADATA
sec_edgar_downloader-5.0.1.dist-info/RECORD
