Metadata-Version: 2.1
Name: sec-edgar-downloader
Version: 5.0.1
Summary: Download SEC filings from the EDGAR database using Python
Keywords: sec,edgar,filing,financial,finance,stocks,mutual-funds,sec.gov
Author-email: Jad Chaar <jad.chaar@gmail.com>
Requires-Python: >=3.8
Classifier: Development Status :: 5 - Production/Stable
Classifier: Intended Audience :: Developers
Classifier: Intended Audience :: Information Technology
Classifier: Intended Audience :: Financial and Insurance Industry
Classifier: Natural Language :: English
Classifier: Topic :: Software Development :: Libraries :: Python Modules
Classifier: Topic :: Office/Business :: Financial
Classifier: Topic :: Office/Business :: Financial :: Investment
Classifier: License :: OSI Approved :: MIT License
Classifier: Programming Language :: Python :: 3
Classifier: Programming Language :: Python :: 3.8
Classifier: Programming Language :: Python :: 3.9
Classifier: Programming Language :: Python :: 3.10
Classifier: Programming Language :: Python :: 3.11
Classifier: Programming Language :: Python :: 3.12
Classifier: Programming Language :: Python :: 3 :: Only
Classifier: Operating System :: OS Independent
Requires-Dist: requests
Requires-Dist: pyrate-limiter>=3.1.0
Requires-Dist: doc8 ; extra == "doc"
Requires-Dist: sphinx ; extra == "doc"
Requires-Dist: sphinx-autobuild ; extra == "doc"
Requires-Dist: sphinx-autodoc-typehints ; extra == "doc"
Requires-Dist: pre-commit ; extra == "test"
Requires-Dist: pytest ; extra == "test"
Requires-Dist: pytest-cov ; extra == "test"
Project-URL: Documentation, https://sec-edgar-downloader.readthedocs.io
Project-URL: Issues, https://github.com/jadchaar/sec-edgar-downloader/issues
Project-URL: Source, https://github.com/jadchaar/sec-edgar-downloader
Provides-Extra: doc
Provides-Extra: test
